[
    {
        "key": "dbln",
        "value": "%7B%2261571360573107%22%3A%22zfjEemSS%22%7D",
        "domain": "facebook.com",
        "path": "/login/device-based/",
        "hostOnly": false,
        "creation": "2024-12-28T14:49:21.863Z",
        "lastAccessed": "2024-12-28T14:49:21.863Z"
    },
    {
        "key": "sb",
        "value": "XI5vZ7BMbx1JKI0lKw-wP2t2",
        "domain": "facebook.com",
        "path": "/",
        "hostOnly": false,
        "creation": "2024-12-28T14:49:21.863Z",
        "lastAccessed": "2024-12-28T14:49:21.863Z"
    },
    {
        "key": "vpd",
        "value": "v1%3B602x324x2.2190306186676025",
        "domain": "facebook.com",
        "path": "/",
        "hostOnly": false,
        "creation": "2024-12-28T14:49:21.863Z",
        "lastAccessed": "2024-12-28T14:49:21.863Z"
    },
    {
        "key": "wl_cbv",
        "value": "v2%3Bclient_version%3A2701%3Btimestamp%3A1735365080",
        "domain": "facebook.com",
        "path": "/",
        "hostOnly": false,
        "creation": "2024-12-28T14:49:21.863Z",
        "lastAccessed": "2024-12-28T14:49:21.863Z"
    },
    {
        "key": "ps_l",
        "value": "1",
        "domain": "facebook.com",
        "path": "/",
        "hostOnly": false,
        "creation": "2024-12-28T14:49:21.863Z",
        "lastAccessed": "2024-12-28T14:49:21.863Z"
    },
    {
        "key": "ps_n",
        "value": "1",
        "domain": "facebook.com",
        "path": "/",
        "hostOnly": false,
        "creation": "2024-12-28T14:49:21.864Z",
        "lastAccessed": "2024-12-28T14:49:21.864Z"
    },
    {
        "key": "dpr",
        "value": "2.4441585540771484",
        "domain": "facebook.com",
        "path": "/",
        "hostOnly": false,
        "creation": "2024-12-28T14:49:21.864Z",
        "lastAccessed": "2024-12-28T14:49:21.864Z"
    },
    {
        "key": "datr",
        "value": "1u5vZ36R0Q6uJau8Cy6tXe4t",
        "domain": "facebook.com",
        "path": "/",
        "hostOnly": false,
        "creation": "2024-12-28T14:49:21.864Z",
        "lastAccessed": "2024-12-28T14:49:21.864Z"
    },
    {
        "key": "locale",
        "value": "en_US",
        "domain": "facebook.com",
        "path": "/",
        "hostOnly": false,
        "creation": "2024-12-28T14:49:21.864Z",
        "lastAccessed": "2024-12-28T14:49:21.864Z"
    },
    {
        "key": "wd",
        "value": "802x1488",
        "domain": "facebook.com",
        "path": "/",
        "hostOnly": false,
        "creation": "2024-12-28T14:49:21.864Z",
        "lastAccessed": "2024-12-28T14:49:21.864Z"
    },
    {
        "key": "c_user",
        "value": "61571360573107",
        "domain": "facebook.com",
        "path": "/",
        "hostOnly": false,
        "creation": "2024-12-28T14:49:21.864Z",
        "lastAccessed": "2024-12-28T14:49:21.864Z"
    },
    {
        "key": "xs",
        "value": "1%3AQ4mXw3cRE-D7SQ%3A2%3A1735397204%3A-1%3A-1",
        "domain": "facebook.com",
        "path": "/",
        "hostOnly": false,
        "creation": "2024-12-28T14:49:21.864Z",
        "lastAccessed": "2024-12-28T14:49:21.864Z"
    },
    {
        "key": "fr",
        "value": "19fiFCyRXoUWZXgGp.AWVPrUSyBMScXtEY3tXoHJQp1p8.Bnb_PW..AAA.0.0.BncA-y.AWVwy8ShCrs",
        "domain": "facebook.com",
        "path": "/",
        "hostOnly": false,
        "creation": "2024-12-28T14:49:21.864Z",
        "lastAccessed": "2024-12-28T14:49:21.864Z"
    },
    {
        "key": "presence",
        "value": "C%7B%22lm3%22%3A%22g.9065670703476089%22%2C%22t3%22%3A%5B%5D%2C%22utc3%22%3A1735397307124%2C%22v%22%3A1%7D",
        "domain": "facebook.com",
        "path": "/",
        "hostOnly": false,
        "creation": "2024-12-28T14:49:21.864Z",
        "lastAccessed": "2024-12-28T14:49:21.864Z"
    }
]
